aiolang/__init__.py
aiolang/aiolang.py
aiolang/exceptions/__init__.py
aiolang/exceptions/exceptions.py
aiolang/language/__init__.py
aiolang/language/langs_text.py
aiolang/language/langs_voice.py
aiolang/language/langs_web.py
aiolang/methods/__init__.py
aiolang/methods/text_to_voice.py
aiolang/methods/translate_text.py
aiolang/network/__init__.py
aiolang/network/network.py
aiolang_python-0.0.2.dist-info/licenses/LICENSE
aiolang_python-0.0.2.dist-info/METADATA
aiolang_python-0.0.2.dist-info/WHEEL
aiolang_python-0.0.2.dist-info/top_level.txt
aiolang_python-0.0.2.dist-info/RECORD
